dynamo_query/__init__.py
dynamo_query/__main__.py
dynamo_query/base_dynamo_query.py
dynamo_query/data_table.py
dynamo_query/dynamo_autoscaler.py
dynamo_query/dynamo_query_main.py
dynamo_query/dynamo_query_types.py
dynamo_query/dynamo_table.py
dynamo_query/dynamo_table_index.py
dynamo_query/enums.py
dynamo_query/expressions.py
dynamo_query/json_tools.py
dynamo_query/lazy_logger.py
dynamo_query/py.typed
dynamo_query/sentinel.py
dynamo_query/utils.py
dynamo_query/version.txt
dynamo_query/dictclasses/__init__.py
dynamo_query/dictclasses/decorators.py
dynamo_query/dictclasses/dictclass.py
dynamo_query/dictclasses/dynamo_dictclass.py
dynamo_query/dictclasses/loose_dictclass.py
dynamoquery-2.11.1.dist-info/LICENSE
dynamoquery-2.11.1.dist-info/METADATA
dynamoquery-2.11.1.dist-info/WHEEL
dynamoquery-2.11.1.dist-info/top_level.txt
dynamoquery-2.11.1.dist-info/RECORD
