Metadata-Version: 2.1
Name: dynamoquery
Version: 2.11.1
Summary: # DynamoQuery
Home-page: https://github.com/altitudenetworks/dynamoquery
Author: Altitude Networks Engineering Team
Author-email: engineering@altitudenetworks.com
License: UNKNOWN
Platform: UNKNOWN
Classifier: Development Status :: 3 - Alpha
Classifier: Intended Audience :: Developers
Classifier: Environment :: Console
Classifier: License :: OSI Approved :: MIT License
Classifier: Natural Language :: English
Classifier: Operating System :: OS Independent
Classifier: Programming Language :: Python :: 3.6
Classifier: Programming Language :: Python :: 3.7
Classifier: Programming Language :: Python :: 3.8
Classifier: Programming Language :: Python :: 3 :: Only
Classifier: Programming Language :: Python :: Implementation :: CPython
Classifier: Typing :: Typed
Requires-Python: >=3.6.10
Requires-Dist: botocore
